kiponos_pysdk/__init__.py
kiponos_pysdk/client.py
kiponos_pysdk/config.py
kiponos_pysdk/utils.py
kiponos_pysdk-0.1.2.dist-info/LICENSE
kiponos_pysdk-0.1.2.dist-info/METADATA
kiponos_pysdk-0.1.2.dist-info/WHEEL
kiponos_pysdk-0.1.2.dist-info/RECORD
