Metadata-Version: 2.3
Name: kiponos-pysdk
Version: 0.1.2
Summary: Kiponos Python SDK for real-time configuration management via WebSocket/STOMP for Kiponos.io
License: Apache-2.0
Keywords: configuration,websocket,stomp,real-time
Author: Moshe Avdiel
Author-email: moshe@kiponos.io
Requires-Python: >=3.12,<4.0
Classifier: License :: OSI Approved :: Apache Software License
Classifier: License :: OSI Approved :: MIT License
Classifier: Operating System :: OS Independent
Classifier: Programming Language :: Python :: 3
Classifier: Programming Language :: Python :: 3.12
Classifier: Programming Language :: Python :: 3.13
Requires-Dist: websocket-client (>=1.8.0,<2.0.0)
Project-URL: Homepage, https://kiponos.io
Project-URL: Repository, https://github.com/Avdiel/kiponos-py-sdk
